{
  "q_44267": {
    "question_id": 44267,
    "post_id": 44256,
    "question_text": "What will be the highest daily number of PLA aircraft tracked by Taiwan's Ministry of National Defense in Taiwan's air-defense identification zone (ADIZ) in July-August 2026?",
    "question_type": "numeric",
    "status": "success",
    "submitted_forecast": [
      0.0,
      0.0063063438566107605,
      0.013823326371971098,
      0.02270302770740492,
      0.03309844921665114,
      0.045159211985958916,
      0.05902665448242217,
      0.07482846681355114,
      0.09267304774644557,
      0.112643814300813,
      0.1347937283433618,
      0.15914032628796215,
      0.1856615434456752,
      0.21429261143945538,
      0.24492427437031342,
      0.27740251760452717,
      0.31152993429797615,
      0.34706877282650983,
      0.3837456182636407,
      0.42125756904871503,
      0.45927968262860075,
      0.4974733876656793,
      0.5354955012455651,
      0.5730074520306394,
      0.6096842974677701,
      0.645223135996304,
      0.679350552689753,
      0.7118287959239666,
      0.7424604588548246,
      0.7710915268486049,
      0.7976127440063179,
      0.8219593419509182,
      0.844109255993467,
      0.8640800225478346,
      0.8819246034807289,
      0.897726415811858,
      0.9115938583083212,
      0.9236546210776287,
      0.9340500425868752,
      0.942929743922309,
      0.9504467264376691,
      0.95675307029428,
      0.9619963216717461,
      0.9663166090555468,
      0.9698444867335799,
      0.9726994684005111,
      0.9749891866859147,
      0.9768090958152846,
      0.9783941603999072,
      0.9799792249845297,
      0.9815642895691522,
      0.9831493541537748,
      0.9847344187383973,
      0.9863194833230198,
      0.9879045479076424,
      0.9894896124922649,
      0.9910746770768875,
      0.9926597416615099,
      0.9942448062461324,
      0.995829870830755,
      0.9974149354153775,
      0.999
    ],
    "reasoning": "Let me work through this systematically.\n\n## (a) Time Left Until Resolution\n\nToday is 2026-07-03. The resolution period is July-August 2026 (specifically after June 30, 2026 and before September 1, 2026). This gives us approximately **59 days** of data collection remaining before resolution.\n\n## (b) Most Likely Outcome and Why\n\nThe question asks for the **highest daily count** in the July-August 2026 window. Based on the research provided:\n\n**Key Data Points:**\n- The PLA increased incursions significantly after May 2024 (Lai's inauguration), reaching \"over 300 per month\"\n- Since early 2026, there has been a **notable decline** to approximately \"200 incursions per month\"\n- This represents a reduction from the 2024-2025 peak but still elevated above historical pre-2024 levels\n- There have been \"noticeable pauses in PLA activity around the ADIZ\" recently, creating uncertainty\n\n**Current Baseline (2026):**\n- Monthly rate: ~200 incursions per month\n- This translates to roughly 6-7 aircraft per day on average\n- However, daily counts are highly variable\n\n**Historical Pattern Recognition:**\nThe research shows an \"upward trendline over the past few years\" until 2024-2025, then a recent decline. The presence of \"pauses\" suggests volatility rather than consistent daily patterns.\n\nThe question is asking specifically for the *highest daily count*, not the average. Even during lower-activity periods, there can be spike days.\n\n## (c) What Would Push the Value Lower?\n\n1. **Continuation of the current 2026 pattern**: If the recent decline/pause trend continues, we might expect daily peaks in the 10-15 range\n2. **Further de-escalation**: Diplomatic improvements or strategic shifts could reduce activity\n3. **PLA resource constraints or other priorities**: Redirection of forces elsewhere\n4. **Seasonal patterns**: If July-August typically sees lower activity (not mentioned in data)\n\n## (d) What Would Push the Value Higher?\n\n1. **Geopolitical escalation**: Any Taiwan-related crisis (election, cross-strait incident, US military activity)\n2. **Return to 2024-2025 patterns**: If the \"pause\" is temporary, we could see spikes back to 20+ daily aircraft\n3. **Coordinated show-of-force operations**: PLA conducting deliberate large-scale operations for signaling\n4. **Seasonal military exercises**: July-August could be exercise season\n5. **Response to specific Taiwan provocations**: Military responses to Taiwan activities\n\n## (e) Base Rate or Historical Reference Values\n\nFrom the CURRENT RESEARCH block, the stated figures are:\n- **2024-2025 peak**: \"over 300 per month\" (roughly 10-15 per day average, with spikes likely higher)\n- **Current 2026 baseline**: \"200 incursions per month\" (roughly 6-7 per day average)\n- The research mentions \"monthly volume\" but doesn't specify the highest single-day record\n\nThe research also notes there's been an overall upward trend historically, but recent reduction since early 2026.\n\n**No specific daily peak data is provided** in the background or research, so I cannot cite a named historical single-day maximum.\n\n## Reasoning for My Estimate\n\nGiven:\n1. Current monthly rate of ~200 means an average of ~6.7 per day\n2. Daily counts are highly variable; peaks are typically 2-3x the average\n3. Historical upward trend suggests previous peaks were in the 15-25 range during 2024-2025\n4. Recent \"pause\" suggests lower current volatility, but could be temporary\n5. The resolution period is July-August, which might coincide with summer military exercises (plausible escalation factor)\n6. No major geopolitical crisis is mentioned in the research for the 2026 timeframe\n7. The trend appears to be toward de-escalation/stabilization rather than further escalation\n\n**Probability Distribution of Daily Peak in July-August 2026:**\n- 10-15 aircraft: 35% (continuation of recent moderated pattern)\n- 16-25 aircraft: 40% (moderate spike, return toward 2024-2025 ranges)\n- 26-40 aircraft: 20% (significant escalation event)\n- 40+ aircraft: 5% (major geopolitical crisis or coordinated large operation)\n\nThe median daily peak is likely in the **18-22 range**, representing a moderate spike above current baseline but not reaching the 2024-2025 levels.\n\n---\n\n**Low (10th percentile): 8**\n**Median (50th percentile): 20**\n**High (90th percentile): 35**",
    "community_prediction": null
  }
}